easyignore/__init__.py
easyignore/__main__.py
easyignore/main.py
easyignore-0.3.2.dist-info/METADATA
easyignore-0.3.2.dist-info/WHEEL
easyignore-0.3.2.dist-info/entry_points.txt
easyignore-0.3.2.dist-info/licenses/LICENSE
easyignore-0.3.2.dist-info/RECORD
