Metadata-Version: 2.4
Name: easyignore
Version: 0.3.2
Summary: Command line interface for generating .gitignore files
Project-URL: homepage, https://github.com/andrew-s28/easyignore
Project-URL: issues, https://github.com/andrew-s28/easyignore/issues
Author-email: Andrew Scherer <scherand@oregonstate.edu>
Maintainer-email: Andrew Scherer <scherand@oregonstate.edu>
License: MIT License
License-File: LICENSE
Classifier: Development Status :: 4 - Beta
Classifier: Intended Audience :: Developers
Classifier: License :: OSI Approved :: MIT License
Classifier: Operating System :: OS Independent
Classifier: Programming Language :: Python
Classifier: Programming Language :: Python :: 3
Classifier: Programming Language :: Python :: 3.10
Classifier: Programming Language :: Python :: 3.11
Classifier: Programming Language :: Python :: 3.12
Classifier: Programming Language :: Python :: 3.13
Classifier: Topic :: Software Development :: Libraries
Classifier: Topic :: Software Development :: Libraries :: Python Modules
Requires-Python: >=3.10
Requires-Dist: requests>=2.32.3
Requires-Dist: shellingham>=1.5.4
Requires-Dist: typer>=0.15.2
